{
  "lastUpdated": "2026-03-16T08:11:59.231Z",
  "platforms": {
    "twitter": {
      "name": "X (Twitter)",
      "icon": "𝕏",
      "items": [
        {
          "rank": 1,
          "title": "#RingRoyale",
          "url": "https://twitter.com/search?q=%23RingRoyale",
          "hot": "",
          "platform": "twitter"
        },
        {
          "rank": 2,
          "title": "#Oscars",
          "url": "https://twitter.com/search?q=%23Oscars",
          "hot": "",
          "platform": "twitter"
        },
        {
          "rank": 3,
          "title": "#تزوج_من_تطبيق_استقرار",
          "url": "https://twitter.com/search?q=%23%D8%AA%D8%B2%D9%88%D8%AC_%D9%85%D9%86_%D8%AA%D8%B7%D8%A8%D9%8A%D9%82_%D8%A7%D8%B3%D8%AA%D9%82%D8%B1%D8%A7%D8%B1",
          "hot": "",
          "platform": "twitter"
        },
        {
          "rank": 4,
          "title": "平和学習",
          "url": "https://twitter.com/search?q=%E5%B9%B3%E5%92%8C%E5%AD%A6%E7%BF%92",
          "hot": "",
          "platform": "twitter"
        },
        {
          "rank": 5,
          "title": "#TleFirstone2ndAnniversary",
          "url": "https://twitter.com/search?q=%23TleFirstone2ndAnniversary",
          "hot": "",
          "platform": "twitter"
        },
        {
          "rank": 6,
          "title": "TFO 2Y ALWAYS HERE TOGETHER",
          "url": "https://twitter.com/search?q=TFO%202Y%20ALWAYS%20HERE%20TOGETHER",
          "hot": "",
          "platform": "twitter"
        },
        {
          "rank": 7,
          "title": "Sinners",
          "url": "https://twitter.com/search?q=Sinners",
          "hot": "",
          "platform": "twitter"
        },
        {
          "rank": 8,
          "title": "#LOLFanFest2026LIVED2",
          "url": "https://twitter.com/search?q=%23LOLFanFest2026LIVED2",
          "hot": "",
          "platform": "twitter"
        },
        {
          "rank": 9,
          "title": "Adame",
          "url": "https://twitter.com/search?q=Adame",
          "hot": "",
          "platform": "twitter"
        },
        {
          "rank": 10,
          "title": "GFPS PRESSTOUR LOL2026",
          "url": "https://twitter.com/search?q=GFPS%20PRESSTOUR%20LOL2026",
          "hot": "",
          "platform": "twitter"
        },
        {
          "rank": 11,
          "title": "Michael B Jordan",
          "url": "https://twitter.com/search?q=Michael%20B%20Jordan",
          "hot": "",
          "platform": "twitter"
        },
        {
          "rank": 12,
          "title": "辺野古沖",
          "url": "https://twitter.com/search?q=%E8%BE%BA%E9%87%8E%E5%8F%A4%E6%B2%96",
          "hot": "",
          "platform": "twitter"
        },
        {
          "rank": 13,
          "title": "Marcela",
          "url": "https://twitter.com/search?q=Marcela",
          "hot": "",
          "platform": "twitter"
        },
        {
          "rank": 14,
          "title": "Siapkan Cadangan BBM",
          "url": "https://twitter.com/search?q=Siapkan%20Cadangan%20BBM",
          "hot": "",
          "platform": "twitter"
        },
        {
          "rank": 15,
          "title": "バンナム",
          "url": "https://twitter.com/search?q=%E3%83%90%E3%83%B3%E3%83%8A%E3%83%A0",
          "hot": "",
          "platform": "twitter"
        },
        {
          "rank": 16,
          "title": "War Trakjil Iphone17Pro",
          "url": "https://twitter.com/search?q=War%20Trakjil%20Iphone17Pro",
          "hot": "",
          "platform": "twitter"
        },
        {
          "rank": 17,
          "title": "死亡の2人",
          "url": "https://twitter.com/search?q=%E6%AD%BB%E4%BA%A1%E3%81%AE2%E4%BA%BA",
          "hot": "",
          "platform": "twitter"
        },
        {
          "rank": 18,
          "title": "Karely",
          "url": "https://twitter.com/search?q=Karely",
          "hot": "",
          "platform": "twitter"
        },
        {
          "rank": 19,
          "title": "Trejo",
          "url": "https://twitter.com/search?q=Trejo",
          "hot": "",
          "platform": "twitter"
        },
        {
          "rank": 20,
          "title": "Javier Bardem",
          "url": "https://twitter.com/search?q=Javier%20Bardem",
          "hot": "",
          "platform": "twitter"
        },
        {
          "rank": 21,
          "title": "抗議活動",
          "url": "https://twitter.com/search?q=%E6%8A%97%E8%AD%B0%E6%B4%BB%E5%8B%95",
          "hot": "",
          "platform": "twitter"
        },
        {
          "rank": 22,
          "title": "同志社国際高校",
          "url": "https://twitter.com/search?q=%E5%90%8C%E5%BF%97%E7%A4%BE%E5%9B%BD%E9%9A%9B%E9%AB%98%E6%A0%A1",
          "hot": "",
          "platform": "twitter"
        },
        {
          "rank": 23,
          "title": "One Battle After Another",
          "url": "https://twitter.com/search?q=One%20Battle%20After%20Another",
          "hot": "",
          "platform": "twitter"
        },
        {
          "rank": 24,
          "title": "Marty Supreme",
          "url": "https://twitter.com/search?q=Marty%20Supreme",
          "hot": "",
          "platform": "twitter"
        },
        {
          "rank": 25,
          "title": "女子高生と男性船長",
          "url": "https://twitter.com/search?q=%E5%A5%B3%E5%AD%90%E9%AB%98%E7%94%9F%E3%81%A8%E7%94%B7%E6%80%A7%E8%88%B9%E9%95%B7",
          "hot": "",
          "platform": "twitter"
        },
        {
          "rank": 26,
          "title": "沖縄タイムス",
          "url": "https://twitter.com/search?q=%E6%B2%96%E7%B8%84%E3%82%BF%E3%82%A4%E3%83%A0%E3%82%B9",
          "hot": "",
          "platform": "twitter"
        },
        {
          "rank": 27,
          "title": "WILLIAMEST LA MAGIC",
          "url": "https://twitter.com/search?q=WILLIAMEST%20LA%20MAGIC",
          "hot": "",
          "platform": "twitter"
        },
        {
          "rank": 28,
          "title": "波浪注意報",
          "url": "https://twitter.com/search?q=%E6%B3%A2%E6%B5%AA%E6%B3%A8%E6%84%8F%E5%A0%B1",
          "hot": "",
          "platform": "twitter"
        },
        {
          "rank": 29,
          "title": "Jessie Buckley",
          "url": "https://twitter.com/search?q=Jessie%20Buckley",
          "hot": "",
          "platform": "twitter"
        },
        {
          "rank": 30,
          "title": "OBAA",
          "url": "https://twitter.com/search?q=OBAA",
          "hot": "",
          "platform": "twitter"
        }
      ]
    },
    "bilibili": {
      "name": "Bilibili",
      "icon": "📺",
      "items": [
        {
          "rank": 1,
          "title": "这就是你想要的长大吗？",
          "url": "https://www.bilibili.com/video/BV1dScmz7ENx",
          "hot": "467万播放",
          "platform": "bilibili"
        },
        {
          "rank": 2,
          "title": "央美一等奖二维动画作品——《谱》",
          "url": "https://www.bilibili.com/video/BV1ezcDzXEUN",
          "hot": "130万播放",
          "platform": "bilibili"
        },
        {
          "rank": 3,
          "title": "我在雪山救了100只狐狸！",
          "url": "https://www.bilibili.com/video/BV15EwWzLEwa",
          "hot": "642万播放",
          "platform": "bilibili"
        },
        {
          "rank": 4,
          "title": "影视飓风VS六位千万博主，躲猫猫大赛奖金10万元！",
          "url": "https://www.bilibili.com/video/BV1Wdc2zsEMp",
          "hot": "547万播放",
          "platform": "bilibili"
        },
        {
          "rank": 5,
          "title": "国外大学食堂交响乐快闪，老哥们真会玩",
          "url": "https://www.bilibili.com/video/BV1ZmcSz4EZx",
          "hot": "381万播放",
          "platform": "bilibili"
        },
        {
          "rank": 6,
          "title": "和AI玩历史猜人物游戏，差点吵起来",
          "url": "https://www.bilibili.com/video/BV1PJwszeEFH",
          "hot": "273万播放",
          "platform": "bilibili"
        },
        {
          "rank": 7,
          "title": "假如我也有一台F1赛车...",
          "url": "https://www.bilibili.com/video/BV19BcUzyExN",
          "hot": "516万播放",
          "platform": "bilibili"
        },
        {
          "rank": 8,
          "title": "“割地、赔款”！伊朗的停火条件万税爷能忍？",
          "url": "https://www.bilibili.com/video/BV1wmwxzPEYr",
          "hot": "332万播放",
          "platform": "bilibili"
        },
        {
          "rank": 9,
          "title": "秦岭户外的中药材确实丰富",
          "url": "https://www.bilibili.com/video/BV164wszZETV",
          "hot": "213万播放",
          "platform": "bilibili"
        },
        {
          "rank": 10,
          "title": "我后悔带朋友去大坝了【三角洲动画】",
          "url": "https://www.bilibili.com/video/BV1uqwtzUEMc",
          "hot": "202万播放",
          "platform": "bilibili"
        },
        {
          "rank": 11,
          "title": "第三套全国中学生广播体操【数学版】这套操有力气",
          "url": "https://www.bilibili.com/video/BV1x7czzME6j",
          "hot": "229万播放",
          "platform": "bilibili"
        },
        {
          "rank": 12,
          "title": "《你以为我荡秋千呢》",
          "url": "https://www.bilibili.com/video/BV1ZJwtzcEV1",
          "hot": "240万播放",
          "platform": "bilibili"
        },
        {
          "rank": 13,
          "title": "埃博拉：丝影杀机与未曾终结的血战",
          "url": "https://www.bilibili.com/video/BV1w9w8z1EUf",
          "hot": "216万播放",
          "platform": "bilibili"
        },
        {
          "rank": 14,
          "title": "在大学被拽入后室的可能性很小但并不为零！mv半还原翻跳 【Brain Rot｜脑蚀】",
          "url": "https://www.bilibili.com/video/BV1x2wEzDEQy",
          "hot": "128万播放",
          "platform": "bilibili"
        },
        {
          "rank": 15,
          "title": "24小时不间断？港口都在运些什么",
          "url": "https://www.bilibili.com/video/BV1hAcUzzETk",
          "hot": "383万播放",
          "platform": "bilibili"
        },
        {
          "rank": 16,
          "title": "不该奖励他的……",
          "url": "https://www.bilibili.com/video/BV1BbwFznEpm",
          "hot": "610万播放",
          "platform": "bilibili"
        },
        {
          "rank": 17,
          "title": "热烈欢迎瞿颖姐姐！看看她带来多少便宜货！！",
          "url": "https://www.bilibili.com/video/BV1nWwFz9EFY",
          "hot": "305万播放",
          "platform": "bilibili"
        },
        {
          "rank": 18,
          "title": "小刀盾的进化之路第一季（完整版）",
          "url": "https://www.bilibili.com/video/BV1tQcDzCEtj",
          "hot": "255万播放",
          "platform": "bilibili"
        },
        {
          "rank": 19,
          "title": "共情到底是诅咒还是奖励？",
          "url": "https://www.bilibili.com/video/BV1V2w4z9EMn",
          "hot": "69万播放",
          "platform": "bilibili"
        },
        {
          "rank": 20,
          "title": "爽文小说都不敢这么写！3.0",
          "url": "https://www.bilibili.com/video/BV1PvwHzdEnW",
          "hot": "146万播放",
          "platform": "bilibili"
        }
      ]
    },
    "instagram": {
      "name": "Instagram",
      "icon": "📷",
      "items": [
        {
          "rank": 1,
          "title": "#love",
          "url": "https://www.instagram.com/explore/tags/love/",
          "hot": "",
          "platform": "instagram"
        },
        {
          "rank": 2,
          "title": "#instagood",
          "url": "https://www.instagram.com/explore/tags/instagood/",
          "hot": "",
          "platform": "instagram"
        },
        {
          "rank": 3,
          "title": "#fashion",
          "url": "https://www.instagram.com/explore/tags/fashion/",
          "hot": "",
          "platform": "instagram"
        },
        {
          "rank": 4,
          "title": "#photooftheday",
          "url": "https://www.instagram.com/explore/tags/photooftheday/",
          "hot": "",
          "platform": "instagram"
        },
        {
          "rank": 5,
          "title": "#photography",
          "url": "https://www.instagram.com/explore/tags/photography/",
          "hot": "",
          "platform": "instagram"
        },
        {
          "rank": 6,
          "title": "#beautiful",
          "url": "https://www.instagram.com/explore/tags/beautiful/",
          "hot": "",
          "platform": "instagram"
        },
        {
          "rank": 7,
          "title": "#art",
          "url": "https://www.instagram.com/explore/tags/art/",
          "hot": "",
          "platform": "instagram"
        },
        {
          "rank": 8,
          "title": "#picoftheday",
          "url": "https://www.instagram.com/explore/tags/picoftheday/",
          "hot": "",
          "platform": "instagram"
        },
        {
          "rank": 9,
          "title": "#nature",
          "url": "https://www.instagram.com/explore/tags/nature/",
          "hot": "",
          "platform": "instagram"
        },
        {
          "rank": 10,
          "title": "#happy",
          "url": "https://www.instagram.com/explore/tags/happy/",
          "hot": "",
          "platform": "instagram"
        },
        {
          "rank": 11,
          "title": "#follow",
          "url": "https://www.instagram.com/explore/tags/follow/",
          "hot": "",
          "platform": "instagram"
        },
        {
          "rank": 12,
          "title": "#travel",
          "url": "https://www.instagram.com/explore/tags/travel/",
          "hot": "",
          "platform": "instagram"
        },
        {
          "rank": 13,
          "title": "#style",
          "url": "https://www.instagram.com/explore/tags/style/",
          "hot": "",
          "platform": "instagram"
        },
        {
          "rank": 14,
          "title": "#instadaily",
          "url": "https://www.instagram.com/explore/tags/instadaily/",
          "hot": "",
          "platform": "instagram"
        },
        {
          "rank": 15,
          "title": "#reels",
          "url": "https://www.instagram.com/explore/tags/reels/",
          "hot": "",
          "platform": "instagram"
        },
        {
          "rank": 16,
          "title": "#like",
          "url": "https://www.instagram.com/explore/tags/like/",
          "hot": "",
          "platform": "instagram"
        },
        {
          "rank": 17,
          "title": "#fitness",
          "url": "https://www.instagram.com/explore/tags/fitness/",
          "hot": "",
          "platform": "instagram"
        },
        {
          "rank": 18,
          "title": "#life",
          "url": "https://www.instagram.com/explore/tags/life/",
          "hot": "",
          "platform": "instagram"
        },
        {
          "rank": 19,
          "title": "#beauty",
          "url": "https://www.instagram.com/explore/tags/beauty/",
          "hot": "",
          "platform": "instagram"
        },
        {
          "rank": 20,
          "title": "#food",
          "url": "https://www.instagram.com/explore/tags/food/",
          "hot": "",
          "platform": "instagram"
        }
      ]
    },
    "zhihu": {
      "name": "知乎",
      "icon": "💡",
      "items": []
    },
    "baidu": {
      "name": "百度热搜",
      "icon": "🔍",
      "items": [
        {
          "rank": 1,
          "title": "一口水井 一种信念",
          "url": "https://www.baidu.com/s?wd=%E4%B8%80%E5%8F%A3%E6%B0%B4%E4%BA%95%20%E4%B8%80%E7%A7%8D%E4%BF%A1%E5%BF%B5",
          "hot": "",
          "platform": "baidu"
        },
        {
          "rank": 2,
          "title": "清明不调休不补班",
          "url": "https://www.baidu.com/s?wd=%E6%B8%85%E6%98%8E%E4%B8%8D%E8%B0%83%E4%BC%91%E4%B8%8D%E8%A1%A5%E7%8F%AD",
          "hot": "",
          "platform": "baidu"
        },
        {
          "rank": 3,
          "title": "又有2个手机品牌官宣涨价",
          "url": "https://www.baidu.com/s?wd=%E5%8F%88%E6%9C%892%E4%B8%AA%E6%89%8B%E6%9C%BA%E5%93%81%E7%89%8C%E5%AE%98%E5%AE%A3%E6%B6%A8%E4%BB%B7",
          "hot": "",
          "platform": "baidu"
        },
        {
          "rank": 4,
          "title": "基本医保参保率巩固在95%",
          "url": "https://www.baidu.com/s?wd=%E5%9F%BA%E6%9C%AC%E5%8C%BB%E4%BF%9D%E5%8F%82%E4%BF%9D%E7%8E%87%E5%B7%A9%E5%9B%BA%E5%9C%A895%25",
          "hot": "",
          "platform": "baidu"
        },
        {
          "rank": 5,
          "title": "男子发现自己长期吃315曝光鸡爪",
          "url": "https://www.baidu.com/s?wd=%E7%94%B7%E5%AD%90%E5%8F%91%E7%8E%B0%E8%87%AA%E5%B7%B1%E9%95%BF%E6%9C%9F%E5%90%83315%E6%9B%9D%E5%85%89%E9%B8%A1%E7%88%AA",
          "hot": "",
          "platform": "baidu"
        },
        {
          "rank": 6,
          "title": "吃野菜的第一批受害者出现了",
          "url": "https://www.baidu.com/s?wd=%E5%90%83%E9%87%8E%E8%8F%9C%E7%9A%84%E7%AC%AC%E4%B8%80%E6%89%B9%E5%8F%97%E5%AE%B3%E8%80%85%E5%87%BA%E7%8E%B0%E4%BA%86",
          "hot": "",
          "platform": "baidu"
        },
        {
          "rank": 7,
          "title": "伊朗称440公斤60%丰度浓缩铀被埋",
          "url": "https://www.baidu.com/s?wd=%E4%BC%8A%E6%9C%97%E7%A7%B0440%E5%85%AC%E6%96%A460%25%E4%B8%B0%E5%BA%A6%E6%B5%93%E7%BC%A9%E9%93%80%E8%A2%AB%E5%9F%8B",
          "hot": "",
          "platform": "baidu"
        },
        {
          "rank": 8,
          "title": "只是看牙医竟然看出了“精神病”",
          "url": "https://www.baidu.com/s?wd=%E5%8F%AA%E6%98%AF%E7%9C%8B%E7%89%99%E5%8C%BB%E7%AB%9F%E7%84%B6%E7%9C%8B%E5%87%BA%E4%BA%86%E2%80%9C%E7%B2%BE%E7%A5%9E%E7%97%85%E2%80%9D",
          "hot": "",
          "platform": "baidu"
        },
        {
          "rank": 9,
          "title": "卖给孩子的可爱卡片竟有上吊暗示",
          "url": "https://www.baidu.com/s?wd=%E5%8D%96%E7%BB%99%E5%AD%A9%E5%AD%90%E7%9A%84%E5%8F%AF%E7%88%B1%E5%8D%A1%E7%89%87%E7%AB%9F%E6%9C%89%E4%B8%8A%E5%90%8A%E6%9A%97%E7%A4%BA",
          "hot": "",
          "platform": "baidu"
        },
        {
          "rank": 10,
          "title": "卧底成二把手的记者315又立功",
          "url": "https://www.baidu.com/s?wd=%E5%8D%A7%E5%BA%95%E6%88%90%E4%BA%8C%E6%8A%8A%E6%89%8B%E7%9A%84%E8%AE%B0%E8%80%85315%E5%8F%88%E7%AB%8B%E5%8A%9F",
          "hot": "",
          "platform": "baidu"
        },
        {
          "rank": 11,
          "title": "漂白鸡爪企业致歉",
          "url": "https://www.baidu.com/s?wd=%E6%BC%82%E7%99%BD%E9%B8%A1%E7%88%AA%E4%BC%81%E4%B8%9A%E8%87%B4%E6%AD%89",
          "hot": "",
          "platform": "baidu"
        },
        {
          "rank": 12,
          "title": "博主发布“甘肃参战”谣言被约谈",
          "url": "https://www.baidu.com/s?wd=%E5%8D%9A%E4%B8%BB%E5%8F%91%E5%B8%83%E2%80%9C%E7%94%98%E8%82%83%E5%8F%82%E6%88%98%E2%80%9D%E8%B0%A3%E8%A8%80%E8%A2%AB%E7%BA%A6%E8%B0%88",
          "hot": "",
          "platform": "baidu"
        },
        {
          "rank": 13,
          "title": "姚晨曹郁离婚",
          "url": "https://www.baidu.com/s?wd=%E5%A7%9A%E6%99%A8%E6%9B%B9%E9%83%81%E7%A6%BB%E5%A9%9A",
          "hot": "",
          "platform": "baidu"
        },
        {
          "rank": 14,
          "title": "霍尔木兹海峡通航船只数量首次降为0",
          "url": "https://www.baidu.com/s?wd=%E9%9C%8D%E5%B0%94%E6%9C%A8%E5%85%B9%E6%B5%B7%E5%B3%A1%E9%80%9A%E8%88%AA%E8%88%B9%E5%8F%AA%E6%95%B0%E9%87%8F%E9%A6%96%E6%AC%A1%E9%99%8D%E4%B8%BA0",
          "hot": "",
          "platform": "baidu"
        },
        {
          "rank": 15,
          "title": "湘雅医院失联学生确认坠江身亡",
          "url": "https://www.baidu.com/s?wd=%E6%B9%98%E9%9B%85%E5%8C%BB%E9%99%A2%E5%A4%B1%E8%81%94%E5%AD%A6%E7%94%9F%E7%A1%AE%E8%AE%A4%E5%9D%A0%E6%B1%9F%E8%BA%AB%E4%BA%A1",
          "hot": "",
          "platform": "baidu"
        },
        {
          "rank": 16,
          "title": "中方：中美就特朗普访华保持着沟通",
          "url": "https://www.baidu.com/s?wd=%E4%B8%AD%E6%96%B9%EF%BC%9A%E4%B8%AD%E7%BE%8E%E5%B0%B1%E7%89%B9%E6%9C%97%E6%99%AE%E8%AE%BF%E5%8D%8E%E4%BF%9D%E6%8C%81%E7%9D%80%E6%B2%9F%E9%80%9A",
          "hot": "",
          "platform": "baidu"
        },
        {
          "rank": 17,
          "title": "捐二战相册的美国小伙宣布定居中国",
          "url": "https://www.baidu.com/s?wd=%E6%8D%90%E4%BA%8C%E6%88%98%E7%9B%B8%E5%86%8C%E7%9A%84%E7%BE%8E%E5%9B%BD%E5%B0%8F%E4%BC%99%E5%AE%A3%E5%B8%83%E5%AE%9A%E5%B1%85%E4%B8%AD%E5%9B%BD",
          "hot": "",
          "platform": "baidu"
        },
        {
          "rank": 18,
          "title": "郑丽文硬怼：北京我去定了",
          "url": "https://www.baidu.com/s?wd=%E9%83%91%E4%B8%BD%E6%96%87%E7%A1%AC%E6%80%BC%EF%BC%9A%E5%8C%97%E4%BA%AC%E6%88%91%E5%8E%BB%E5%AE%9A%E4%BA%86",
          "hot": "",
          "platform": "baidu"
        },
        {
          "rank": 19,
          "title": "部分茶叶咖啡中检出伟哥成分",
          "url": "https://www.baidu.com/s?wd=%E9%83%A8%E5%88%86%E8%8C%B6%E5%8F%B6%E5%92%96%E5%95%A1%E4%B8%AD%E6%A3%80%E5%87%BA%E4%BC%9F%E5%93%A5%E6%88%90%E5%88%86",
          "hot": "",
          "platform": "baidu"
        },
        {
          "rank": 20,
          "title": "黄金和手机卖爆 你的钱包参与了吗",
          "url": "https://www.baidu.com/s?wd=%E9%BB%84%E9%87%91%E5%92%8C%E6%89%8B%E6%9C%BA%E5%8D%96%E7%88%86%20%E4%BD%A0%E7%9A%84%E9%92%B1%E5%8C%85%E5%8F%82%E4%B8%8E%E4%BA%86%E5%90%97",
          "hot": "",
          "platform": "baidu"
        },
        {
          "rank": 21,
          "title": "外交部回应中朝恢复客运航班",
          "url": "https://www.baidu.com/s?wd=%E5%A4%96%E4%BA%A4%E9%83%A8%E5%9B%9E%E5%BA%94%E4%B8%AD%E6%9C%9D%E6%81%A2%E5%A4%8D%E5%AE%A2%E8%BF%90%E8%88%AA%E7%8F%AD",
          "hot": "",
          "platform": "baidu"
        },
        {
          "rank": 22,
          "title": "人民日报评“做核磁共振被忘6小时”",
          "url": "https://www.baidu.com/s?wd=%E4%BA%BA%E6%B0%91%E6%97%A5%E6%8A%A5%E8%AF%84%E2%80%9C%E5%81%9A%E6%A0%B8%E7%A3%81%E5%85%B1%E6%8C%AF%E8%A2%AB%E5%BF%986%E5%B0%8F%E6%97%B6%E2%80%9D",
          "hot": "",
          "platform": "baidu"
        },
        {
          "rank": 23,
          "title": "儿子生前砍的柴放8年妈妈舍不得用",
          "url": "https://www.baidu.com/s?wd=%E5%84%BF%E5%AD%90%E7%94%9F%E5%89%8D%E7%A0%8D%E7%9A%84%E6%9F%B4%E6%94%BE8%E5%B9%B4%E5%A6%88%E5%A6%88%E8%88%8D%E4%B8%8D%E5%BE%97%E7%94%A8",
          "hot": "",
          "platform": "baidu"
        },
        {
          "rank": 24,
          "title": "黄金白银再现断崖式跳水",
          "url": "https://www.baidu.com/s?wd=%E9%BB%84%E9%87%91%E7%99%BD%E9%93%B6%E5%86%8D%E7%8E%B0%E6%96%AD%E5%B4%96%E5%BC%8F%E8%B7%B3%E6%B0%B4",
          "hot": "",
          "platform": "baidu"
        },
        {
          "rank": 25,
          "title": "外孙称“315晚会应该曝光我外婆”",
          "url": "https://www.baidu.com/s?wd=%E5%A4%96%E5%AD%99%E7%A7%B0%E2%80%9C315%E6%99%9A%E4%BC%9A%E5%BA%94%E8%AF%A5%E6%9B%9D%E5%85%89%E6%88%91%E5%A4%96%E5%A9%86%E2%80%9D",
          "hot": "",
          "platform": "baidu"
        },
        {
          "rank": 26,
          "title": "“超级央行周”来临",
          "url": "https://www.baidu.com/s?wd=%E2%80%9C%E8%B6%85%E7%BA%A7%E5%A4%AE%E8%A1%8C%E5%91%A8%E2%80%9D%E6%9D%A5%E4%B8%B4",
          "hot": "",
          "platform": "baidu"
        },
        {
          "rank": 27,
          "title": "夫妻结婚54年打呼噜也不分床睡",
          "url": "https://www.baidu.com/s?wd=%E5%A4%AB%E5%A6%BB%E7%BB%93%E5%A9%9A54%E5%B9%B4%E6%89%93%E5%91%BC%E5%99%9C%E4%B9%9F%E4%B8%8D%E5%88%86%E5%BA%8A%E7%9D%A1",
          "hot": "",
          "platform": "baidu"
        },
        {
          "rank": 28,
          "title": "茅台是时候走下神坛了",
          "url": "https://www.baidu.com/s?wd=%E8%8C%85%E5%8F%B0%E6%98%AF%E6%97%B6%E5%80%99%E8%B5%B0%E4%B8%8B%E7%A5%9E%E5%9D%9B%E4%BA%86",
          "hot": "",
          "platform": "baidu"
        },
        {
          "rank": 29,
          "title": "黄天鹅：从未添加任何人工合成色素",
          "url": "https://www.baidu.com/s?wd=%E9%BB%84%E5%A4%A9%E9%B9%85%EF%BC%9A%E4%BB%8E%E6%9C%AA%E6%B7%BB%E5%8A%A0%E4%BB%BB%E4%BD%95%E4%BA%BA%E5%B7%A5%E5%90%88%E6%88%90%E8%89%B2%E7%B4%A0",
          "hot": "",
          "platform": "baidu"
        },
        {
          "rank": 30,
          "title": "孩子私售45克金饰 商家只给了2.8万",
          "url": "https://www.baidu.com/s?wd=%E5%AD%A9%E5%AD%90%E7%A7%81%E5%94%AE45%E5%85%8B%E9%87%91%E9%A5%B0%20%E5%95%86%E5%AE%B6%E5%8F%AA%E7%BB%99%E4%BA%862.8%E4%B8%87",
          "hot": "",
          "platform": "baidu"
        }
      ]
    },
    "toutiao": {
      "name": "今日头条",
      "icon": "📰",
      "items": [
        {
          "rank": 1,
          "title": "被315点名亿丰电子已停止生产经营",
          "url": "https://www.toutiao.com/trending/7617547350860595242/?category_name=topic_innerflow&event_type=hot_board&log_pb=%7B%22category_name%22%3A%22topic_innerflow%22%2C%22cluster_type%22%3A%2210%22%2C%22enter_from%22%3A%22click_category%22%2C%22entrance_hotspot%22%3A%22outside%22%2C%22event_type%22%3A%22hot_board%22%2C%22hot_board_cluster_id%22%3A%227617547350860595242%22%2C%22hot_board_impr_id%22%3A%222026031616112915E2A6A4DD8510E97683%22%2C%22jump_page%22%3A%22hot_board_page%22%2C%22location%22%3A%22news_hot_card%22%2C%22page_location%22%3A%22hot_board_page%22%2C%22source%22%3A%22trending_tab%22%2C%22style_id%22%3A%2240132%22%2C%22title%22%3A%22%E8%A2%AB315%E7%82%B9%E5%90%8D%E4%BA%BF%E4%B8%B0%E7%94%B5%E5%AD%90%E5%B7%B2%E5%81%9C%E6%AD%A2%E7%94%9F%E4%BA%A7%E7%BB%8F%E8%90%A5%22%7D&rank=&style_id=40132&topic_id=7617547350860595242",
          "hot": "4142万",
          "platform": "toutiao"
        },
        {
          "rank": 2,
          "title": "埃文·凯尔宣布定居中国",
          "url": "https://www.toutiao.com/trending/7617023176892186633/?category_name=topic_innerflow&event_type=hot_board&log_pb=%7B%22category_name%22%3A%22topic_innerflow%22%2C%22cluster_type%22%3A%226%22%2C%22enter_from%22%3A%22click_category%22%2C%22entrance_hotspot%22%3A%22outside%22%2C%22event_type%22%3A%22hot_board%22%2C%22hot_board_cluster_id%22%3A%227617023176892186633%22%2C%22hot_board_impr_id%22%3A%222026031616112915E2A6A4DD8510E97683%22%2C%22jump_page%22%3A%22hot_board_page%22%2C%22location%22%3A%22news_hot_card%22%2C%22page_location%22%3A%22hot_board_page%22%2C%22source%22%3A%22trending_tab%22%2C%22style_id%22%3A%2240132%22%2C%22title%22%3A%22%E5%9F%83%E6%96%87%C2%B7%E5%87%AF%E5%B0%94%E5%AE%A3%E5%B8%83%E5%AE%9A%E5%B1%85%E4%B8%AD%E5%9B%BD%22%7D&rank=&style_id=40132&topic_id=7617023176892186633",
          "hot": "3748万",
          "platform": "toutiao"
        },
        {
          "rank": 3,
          "title": "树立和践行正确政绩观",
          "url": "https://www.toutiao.com/article/7617076089157403174",
          "hot": "3391万",
          "platform": "toutiao"
        },
        {
          "rank": 4,
          "title": "315曝光的鸡爪公司股东也在看晚会",
          "url": "https://www.toutiao.com/trending/7617682436520119846/?category_name=topic_innerflow&event_type=hot_board&log_pb=%7B%22category_name%22%3A%22topic_innerflow%22%2C%22cluster_type%22%3A%222%22%2C%22enter_from%22%3A%22click_category%22%2C%22entrance_hotspot%22%3A%22outside%22%2C%22event_type%22%3A%22hot_board%22%2C%22hot_board_cluster_id%22%3A%227617682436520119846%22%2C%22hot_board_impr_id%22%3A%222026031616112915E2A6A4DD8510E97683%22%2C%22jump_page%22%3A%22hot_board_page%22%2C%22location%22%3A%22news_hot_card%22%2C%22page_location%22%3A%22hot_board_page%22%2C%22source%22%3A%22trending_tab%22%2C%22style_id%22%3A%2240132%22%2C%22title%22%3A%22315%E6%9B%9D%E5%85%89%E7%9A%84%E9%B8%A1%E7%88%AA%E5%85%AC%E5%8F%B8%E8%82%A1%E4%B8%9C%E4%B9%9F%E5%9C%A8%E7%9C%8B%E6%99%9A%E4%BC%9A%22%7D&rank=&style_id=40132&topic_id=7617682436520119846",
          "hot": "3068万",
          "platform": "toutiao"
        },
        {
          "rank": 5,
          "title": "美国一男子拔枪反抗被警察击毙",
          "url": "https://www.toutiao.com/trending/7616610541319520266/?category_name=topic_innerflow&event_type=hot_board&log_pb=%7B%22category_name%22%3A%22topic_innerflow%22%2C%22cluster_type%22%3A%226%22%2C%22enter_from%22%3A%22click_category%22%2C%22entrance_hotspot%22%3A%22outside%22%2C%22event_type%22%3A%22hot_board%22%2C%22hot_board_cluster_id%22%3A%227616610541319520266%22%2C%22hot_board_impr_id%22%3A%222026031616112915E2A6A4DD8510E97683%22%2C%22jump_page%22%3A%22hot_board_page%22%2C%22location%22%3A%22news_hot_card%22%2C%22page_location%22%3A%22hot_board_page%22%2C%22source%22%3A%22trending_tab%22%2C%22style_id%22%3A%2240132%22%2C%22title%22%3A%22%E7%BE%8E%E5%9B%BD%E4%B8%80%E7%94%B7%E5%AD%90%E6%8B%94%E6%9E%AA%E5%8F%8D%E6%8A%97%E8%A2%AB%E8%AD%A6%E5%AF%9F%E5%87%BB%E6%AF%99%22%7D&rank=&style_id=40132&topic_id=7616610541319520266",
          "hot": "2776万",
          "platform": "toutiao"
        },
        {
          "rank": 6,
          "title": "英媒：霍尔木兹海峡首次无船通航",
          "url": "https://www.toutiao.com/trending/7617699054671105578/?category_name=topic_innerflow&event_type=hot_board&log_pb=%7B%22category_name%22%3A%22topic_innerflow%22%2C%22cluster_type%22%3A%225%22%2C%22enter_from%22%3A%22click_category%22%2C%22entrance_hotspot%22%3A%22outside%22%2C%22event_type%22%3A%22hot_board%22%2C%22hot_board_cluster_id%22%3A%227617699054671105578%22%2C%22hot_board_impr_id%22%3A%222026031616112915E2A6A4DD8510E97683%22%2C%22jump_page%22%3A%22hot_board_page%22%2C%22location%22%3A%22news_hot_card%22%2C%22page_location%22%3A%22hot_board_page%22%2C%22source%22%3A%22trending_tab%22%2C%22style_id%22%3A%2240132%22%2C%22title%22%3A%22%E8%8B%B1%E5%AA%92%EF%BC%9A%E9%9C%8D%E5%B0%94%E6%9C%A8%E5%85%B9%E6%B5%B7%E5%B3%A1%E9%A6%96%E6%AC%A1%E6%97%A0%E8%88%B9%E9%80%9A%E8%88%AA%22%7D&rank=&style_id=40132&topic_id=7617699054671105578",
          "hot": "2512万",
          "platform": "toutiao"
        },
        {
          "rank": 7,
          "title": "民调：特朗普正将美国盟友推向中国",
          "url": "https://www.toutiao.com/trending/7617510305036795923/?category_name=topic_innerflow&event_type=hot_board&log_pb=%7B%22category_name%22%3A%22topic_innerflow%22%2C%22cluster_type%22%3A%220%22%2C%22enter_from%22%3A%22click_category%22%2C%22entrance_hotspot%22%3A%22outside%22%2C%22event_type%22%3A%22hot_board%22%2C%22hot_board_cluster_id%22%3A%227617510305036795923%22%2C%22hot_board_impr_id%22%3A%222026031616112915E2A6A4DD8510E97683%22%2C%22jump_page%22%3A%22hot_board_page%22%2C%22location%22%3A%22news_hot_card%22%2C%22page_location%22%3A%22hot_board_page%22%2C%22source%22%3A%22trending_tab%22%2C%22style_id%22%3A%2240132%22%2C%22title%22%3A%22%E6%B0%91%E8%B0%83%EF%BC%9A%E7%89%B9%E6%9C%97%E6%99%AE%E6%AD%A3%E5%B0%86%E7%BE%8E%E5%9B%BD%E7%9B%9F%E5%8F%8B%E6%8E%A8%E5%90%91%E4%B8%AD%E5%9B%BD%22%7D&rank=&style_id=40132&topic_id=7617510305036795923",
          "hot": "2273万",
          "platform": "toutiao"
        },
        {
          "rank": 8,
          "title": "美宜佳被查获非法卷烟139.99万支",
          "url": "https://www.toutiao.com/trending/7617370414004813860/?category_name=topic_innerflow&event_type=hot_board&log_pb=%7B%22category_name%22%3A%22topic_innerflow%22%2C%22cluster_type%22%3A%221%22%2C%22enter_from%22%3A%22click_category%22%2C%22entrance_hotspot%22%3A%22outside%22%2C%22event_type%22%3A%22hot_board%22%2C%22hot_board_cluster_id%22%3A%227617370414004813860%22%2C%22hot_board_impr_id%22%3A%222026031616112915E2A6A4DD8510E97683%22%2C%22jump_page%22%3A%22hot_board_page%22%2C%22location%22%3A%22news_hot_card%22%2C%22page_location%22%3A%22hot_board_page%22%2C%22source%22%3A%22trending_tab%22%2C%22style_id%22%3A%2240132%22%2C%22title%22%3A%22%E7%BE%8E%E5%AE%9C%E4%BD%B3%E8%A2%AB%E6%9F%A5%E8%8E%B7%E9%9D%9E%E6%B3%95%E5%8D%B7%E7%83%9F139.99%E4%B8%87%E6%94%AF%22%7D&rank=&style_id=40132&topic_id=7617370414004813860",
          "hot": "2057万",
          "platform": "toutiao"
        },
        {
          "rank": 9,
          "title": "生活职场中你会划清边界吗",
          "url": "https://www.toutiao.com/trending/7617369024510492678/?category_name=topic_innerflow&event_type=hot_board&log_pb=%7B%22category_name%22%3A%22topic_innerflow%22%2C%22cluster_type%22%3A%2210%22%2C%22enter_from%22%3A%22click_category%22%2C%22entrance_hotspot%22%3A%22outside%22%2C%22event_type%22%3A%22hot_board%22%2C%22hot_board_cluster_id%22%3A%227617369024510492678%22%2C%22hot_board_impr_id%22%3A%222026031616112915E2A6A4DD8510E97683%22%2C%22jump_page%22%3A%22hot_board_page%22%2C%22location%22%3A%22news_hot_card%22%2C%22page_location%22%3A%22hot_board_page%22%2C%22source%22%3A%22trending_tab%22%2C%22style_id%22%3A%2240132%22%2C%22title%22%3A%22%E7%94%9F%E6%B4%BB%E8%81%8C%E5%9C%BA%E4%B8%AD%E4%BD%A0%E4%BC%9A%E5%88%92%E6%B8%85%E8%BE%B9%E7%95%8C%E5%90%97%22%7D&rank=&style_id=40132&topic_id=7617369024510492678",
          "hot": "1861万",
          "platform": "toutiao"
        },
        {
          "rank": 10,
          "title": "村民回应在家宰猪后村口售卖被罚5千",
          "url": "https://www.toutiao.com/trending/7617213238614478378/?category_name=topic_innerflow&event_type=hot_board&log_pb=%7B%22category_name%22%3A%22topic_innerflow%22%2C%22cluster_type%22%3A%222%22%2C%22enter_from%22%3A%22click_category%22%2C%22entrance_hotspot%22%3A%22outside%22%2C%22event_type%22%3A%22hot_board%22%2C%22hot_board_cluster_id%22%3A%227617213238614478378%22%2C%22hot_board_impr_id%22%3A%222026031616112915E2A6A4DD8510E97683%22%2C%22jump_page%22%3A%22hot_board_page%22%2C%22location%22%3A%22news_hot_card%22%2C%22page_location%22%3A%22hot_board_page%22%2C%22source%22%3A%22trending_tab%22%2C%22style_id%22%3A%2240132%22%2C%22title%22%3A%22%E6%9D%91%E6%B0%91%E5%9B%9E%E5%BA%94%E5%9C%A8%E5%AE%B6%E5%AE%B0%E7%8C%AA%E5%90%8E%E6%9D%91%E5%8F%A3%E5%94%AE%E5%8D%96%E8%A2%AB%E7%BD%9A5%E5%8D%83%22%7D&rank=&style_id=40132&topic_id=7617213238614478378",
          "hot": "1684万",
          "platform": "toutiao"
        },
        {
          "rank": 11,
          "title": "姚晨曹郁官宣离婚",
          "url": "https://www.toutiao.com/trending/7616697623881695238/?category_name=topic_innerflow&event_type=hot_board&log_pb=%7B%22category_name%22%3A%22topic_innerflow%22%2C%22cluster_type%22%3A%222%22%2C%22enter_from%22%3A%22click_category%22%2C%22entrance_hotspot%22%3A%22outside%22%2C%22event_type%22%3A%22hot_board%22%2C%22hot_board_cluster_id%22%3A%227616697623881695238%22%2C%22hot_board_impr_id%22%3A%222026031616112915E2A6A4DD8510E97683%22%2C%22jump_page%22%3A%22hot_board_page%22%2C%22location%22%3A%22news_hot_card%22%2C%22page_location%22%3A%22hot_board_page%22%2C%22source%22%3A%22trending_tab%22%2C%22style_id%22%3A%2240132%22%2C%22title%22%3A%22%E5%A7%9A%E6%99%A8%E6%9B%B9%E9%83%81%E5%AE%98%E5%AE%A3%E7%A6%BB%E5%A9%9A%22%7D&rank=&style_id=40132&topic_id=7616697623881695238",
          "hot": "1523万",
          "platform": "toutiao"
        },
        {
          "rank": 12,
          "title": "多款保健茶叶咖啡添加“伟哥”成分",
          "url": "https://www.toutiao.com/trending/7617340284222750729/?category_name=topic_innerflow&event_type=hot_board&log_pb=%7B%22category_name%22%3A%22topic_innerflow%22%2C%22cluster_type%22%3A%221%22%2C%22enter_from%22%3A%22click_category%22%2C%22entrance_hotspot%22%3A%22outside%22%2C%22event_type%22%3A%22hot_board%22%2C%22hot_board_cluster_id%22%3A%227617340284222750729%22%2C%22hot_board_impr_id%22%3A%222026031616112915E2A6A4DD8510E97683%22%2C%22jump_page%22%3A%22hot_board_page%22%2C%22location%22%3A%22news_hot_card%22%2C%22page_location%22%3A%22hot_board_page%22%2C%22source%22%3A%22trending_tab%22%2C%22style_id%22%3A%2240132%22%2C%22title%22%3A%22%E5%A4%9A%E6%AC%BE%E4%BF%9D%E5%81%A5%E8%8C%B6%E5%8F%B6%E5%92%96%E5%95%A1%E6%B7%BB%E5%8A%A0%E2%80%9C%E4%BC%9F%E5%93%A5%E2%80%9D%E6%88%90%E5%88%86%22%7D&rank=&style_id=40132&topic_id=7617340284222750729",
          "hot": "1378万",
          "platform": "toutiao"
        },
        {
          "rank": 13,
          "title": "伊朗称目前发射导弹多为10年前生产",
          "url": "https://www.toutiao.com/trending/7616976559953723430/?category_name=topic_innerflow&event_type=hot_board&log_pb=%7B%22category_name%22%3A%22topic_innerflow%22%2C%22cluster_type%22%3A%222%22%2C%22enter_from%22%3A%22click_category%22%2C%22entrance_hotspot%22%3A%22outside%22%2C%22event_type%22%3A%22hot_board%22%2C%22hot_board_cluster_id%22%3A%227616976559953723430%22%2C%22hot_board_impr_id%22%3A%222026031616112915E2A6A4DD8510E97683%22%2C%22jump_page%22%3A%22hot_board_page%22%2C%22location%22%3A%22news_hot_card%22%2C%22page_location%22%3A%22hot_board_page%22%2C%22source%22%3A%22trending_tab%22%2C%22style_id%22%3A%2240132%22%2C%22title%22%3A%22%E4%BC%8A%E6%9C%97%E7%A7%B0%E7%9B%AE%E5%89%8D%E5%8F%91%E5%B0%84%E5%AF%BC%E5%BC%B9%E5%A4%9A%E4%B8%BA10%E5%B9%B4%E5%89%8D%E7%94%9F%E4%BA%A7%22%7D&rank=&style_id=40132&topic_id=7616976559953723430",
          "hot": "1247万",
          "platform": "toutiao"
        },
        {
          "rank": 14,
          "title": "湘雅医院坠江身亡研究生疑留下遗言",
          "url": "https://www.toutiao.com/trending/7617727350708375066/?category_name=topic_innerflow&event_type=hot_board&log_pb=%7B%22category_name%22%3A%22topic_innerflow%22%2C%22cluster_type%22%3A%225%22%2C%22enter_from%22%3A%22click_category%22%2C%22entrance_hotspot%22%3A%22outside%22%2C%22event_type%22%3A%22hot_board%22%2C%22hot_board_cluster_id%22%3A%227617727350708375066%22%2C%22hot_board_impr_id%22%3A%222026031616112915E2A6A4DD8510E97683%22%2C%22jump_page%22%3A%22hot_board_page%22%2C%22location%22%3A%22news_hot_card%22%2C%22page_location%22%3A%22hot_board_page%22%2C%22source%22%3A%22trending_tab%22%2C%22style_id%22%3A%2240132%22%2C%22title%22%3A%22%E6%B9%98%E9%9B%85%E5%8C%BB%E9%99%A2%E5%9D%A0%E6%B1%9F%E8%BA%AB%E4%BA%A1%E7%A0%94%E7%A9%B6%E7%94%9F%E7%96%91%E7%95%99%E4%B8%8B%E9%81%97%E8%A8%80%22%7D&rank=&style_id=40132&topic_id=7617727350708375066",
          "hot": "1129万",
          "platform": "toutiao"
        },
        {
          "rank": 15,
          "title": "你认为按每平方米收物业费合理吗",
          "url": "https://www.toutiao.com/trending/7617373913181863955/?category_name=topic_innerflow&event_type=hot_board&log_pb=%7B%22category_name%22%3A%22topic_innerflow%22%2C%22cluster_type%22%3A%2210%22%2C%22enter_from%22%3A%22click_category%22%2C%22entrance_hotspot%22%3A%22outside%22%2C%22event_type%22%3A%22hot_board%22%2C%22hot_board_cluster_id%22%3A%227617373913181863955%22%2C%22hot_board_impr_id%22%3A%222026031616112915E2A6A4DD8510E97683%22%2C%22jump_page%22%3A%22hot_board_page%22%2C%22location%22%3A%22news_hot_card%22%2C%22page_location%22%3A%22hot_board_page%22%2C%22source%22%3A%22trending_tab%22%2C%22style_id%22%3A%2240132%22%2C%22title%22%3A%22%E4%BD%A0%E8%AE%A4%E4%B8%BA%E6%8C%89%E6%AF%8F%E5%B9%B3%E6%96%B9%E7%B1%B3%E6%94%B6%E7%89%A9%E4%B8%9A%E8%B4%B9%E5%90%88%E7%90%86%E5%90%97%22%7D&rank=&style_id=40132&topic_id=7617373913181863955",
          "hot": "1021万",
          "platform": "toutiao"
        },
        {
          "rank": 16,
          "title": "宝宝抗拒吃辅食 爸爸尝后直接吐了",
          "url": "https://www.toutiao.com/trending/7616846058513580059/?category_name=topic_innerflow&event_type=hot_board&log_pb=%7B%22category_name%22%3A%22topic_innerflow%22%2C%22cluster_type%22%3A%226%22%2C%22enter_from%22%3A%22click_category%22%2C%22entrance_hotspot%22%3A%22outside%22%2C%22event_type%22%3A%22hot_board%22%2C%22hot_board_cluster_id%22%3A%227616846058513580059%22%2C%22hot_board_impr_id%22%3A%222026031616112915E2A6A4DD8510E97683%22%2C%22jump_page%22%3A%22hot_board_page%22%2C%22location%22%3A%22news_hot_card%22%2C%22page_location%22%3A%22hot_board_page%22%2C%22source%22%3A%22trending_tab%22%2C%22style_id%22%3A%2240132%22%2C%22title%22%3A%22%E5%AE%9D%E5%AE%9D%E6%8A%97%E6%8B%92%E5%90%83%E8%BE%85%E9%A3%9F+%E7%88%B8%E7%88%B8%E5%B0%9D%E5%90%8E%E7%9B%B4%E6%8E%A5%E5%90%90%E4%BA%86%22%7D&rank=&style_id=40132&topic_id=7616846058513580059",
          "hot": "924万",
          "platform": "toutiao"
        },
        {
          "rank": 17,
          "title": "湘雅医院失联学生确认坠江身亡",
          "url": "https://www.toutiao.com/trending/7617673110095056410/?category_name=topic_innerflow&event_type=hot_board&log_pb=%7B%22category_name%22%3A%22topic_innerflow%22%2C%22cluster_type%22%3A%221%22%2C%22enter_from%22%3A%22click_category%22%2C%22entrance_hotspot%22%3A%22outside%22%2C%22event_type%22%3A%22hot_board%22%2C%22hot_board_cluster_id%22%3A%227617673110095056410%22%2C%22hot_board_impr_id%22%3A%222026031616112915E2A6A4DD8510E97683%22%2C%22jump_page%22%3A%22hot_board_page%22%2C%22location%22%3A%22news_hot_card%22%2C%22page_location%22%3A%22hot_board_page%22%2C%22source%22%3A%22trending_tab%22%2C%22style_id%22%3A%2240132%22%2C%22title%22%3A%22%E6%B9%98%E9%9B%85%E5%8C%BB%E9%99%A2%E5%A4%B1%E8%81%94%E5%AD%A6%E7%94%9F%E7%A1%AE%E8%AE%A4%E5%9D%A0%E6%B1%9F%E8%BA%AB%E4%BA%A1%22%7D&rank=&style_id=40132&topic_id=7617673110095056410",
          "hot": "836万",
          "platform": "toutiao"
        },
        {
          "rank": 18,
          "title": "伊朗称同时打击美军4个空军基地",
          "url": "https://www.toutiao.com/trending/7616705806347780147/?category_name=topic_innerflow&event_type=hot_board&log_pb=%7B%22category_name%22%3A%22topic_innerflow%22%2C%22cluster_type%22%3A%226%22%2C%22enter_from%22%3A%22click_category%22%2C%22entrance_hotspot%22%3A%22outside%22%2C%22event_type%22%3A%22hot_board%22%2C%22hot_board_cluster_id%22%3A%227616705806347780147%22%2C%22hot_board_impr_id%22%3A%222026031616112915E2A6A4DD8510E97683%22%2C%22jump_page%22%3A%22hot_board_page%22%2C%22location%22%3A%22news_hot_card%22%2C%22page_location%22%3A%22hot_board_page%22%2C%22source%22%3A%22trending_tab%22%2C%22style_id%22%3A%2240132%22%2C%22title%22%3A%22%E4%BC%8A%E6%9C%97%E7%A7%B0%E5%90%8C%E6%97%B6%E6%89%93%E5%87%BB%E7%BE%8E%E5%86%9B4%E4%B8%AA%E7%A9%BA%E5%86%9B%E5%9F%BA%E5%9C%B0%22%7D&rank=&style_id=40132&topic_id=7616705806347780147",
          "hot": "756万",
          "platform": "toutiao"
        },
        {
          "rank": 19,
          "title": "马斯克：人生不需要晴天朋友",
          "url": "https://www.toutiao.com/trending/7616405377337278518/?category_name=topic_innerflow&event_type=hot_board&log_pb=%7B%22category_name%22%3A%22topic_innerflow%22%2C%22cluster_type%22%3A%224%22%2C%22enter_from%22%3A%22click_category%22%2C%22entrance_hotspot%22%3A%22outside%22%2C%22event_type%22%3A%22hot_board%22%2C%22hot_board_cluster_id%22%3A%227616405377337278518%22%2C%22hot_board_impr_id%22%3A%222026031616112915E2A6A4DD8510E97683%22%2C%22jump_page%22%3A%22hot_board_page%22%2C%22location%22%3A%22news_hot_card%22%2C%22page_location%22%3A%22hot_board_page%22%2C%22source%22%3A%22trending_tab%22%2C%22style_id%22%3A%2240132%22%2C%22title%22%3A%22%E9%A9%AC%E6%96%AF%E5%85%8B%EF%BC%9A%E4%BA%BA%E7%94%9F%E4%B8%8D%E9%9C%80%E8%A6%81%E6%99%B4%E5%A4%A9%E6%9C%8B%E5%8F%8B%22%7D&rank=&style_id=40132&topic_id=7616405377337278518",
          "hot": "684万",
          "platform": "toutiao"
        },
        {
          "rank": 20,
          "title": "漂白鸡爪企业致歉",
          "url": "https://www.toutiao.com/trending/7617456406274457663/?category_name=topic_innerflow&event_type=hot_board&log_pb=%7B%22category_name%22%3A%22topic_innerflow%22%2C%22cluster_type%22%3A%222%22%2C%22enter_from%22%3A%22click_category%22%2C%22entrance_hotspot%22%3A%22outside%22%2C%22event_type%22%3A%22hot_board%22%2C%22hot_board_cluster_id%22%3A%227617456406274457663%22%2C%22hot_board_impr_id%22%3A%222026031616112915E2A6A4DD8510E97683%22%2C%22jump_page%22%3A%22hot_board_page%22%2C%22location%22%3A%22news_hot_card%22%2C%22page_location%22%3A%22hot_board_page%22%2C%22source%22%3A%22trending_tab%22%2C%22style_id%22%3A%2240132%22%2C%22title%22%3A%22%E6%BC%82%E7%99%BD%E9%B8%A1%E7%88%AA%E4%BC%81%E4%B8%9A%E8%87%B4%E6%AD%89%22%7D&rank=&style_id=40132&topic_id=7617456406274457663",
          "hot": "619万",
          "platform": "toutiao"
        },
        {
          "rank": 21,
          "title": "男孩拿塑料圈当飞镖砸中路人被拖拽",
          "url": "https://www.toutiao.com/trending/7617673858539356211/?category_name=topic_innerflow&event_type=hot_board&log_pb=%7B%22category_name%22%3A%22topic_innerflow%22%2C%22cluster_type%22%3A%226%22%2C%22enter_from%22%3A%22click_category%22%2C%22entrance_hotspot%22%3A%22outside%22%2C%22event_type%22%3A%22hot_board%22%2C%22hot_board_cluster_id%22%3A%227617673858539356211%22%2C%22hot_board_impr_id%22%3A%222026031616112915E2A6A4DD8510E97683%22%2C%22jump_page%22%3A%22hot_board_page%22%2C%22location%22%3A%22news_hot_card%22%2C%22page_location%22%3A%22hot_board_page%22%2C%22source%22%3A%22trending_tab%22%2C%22style_id%22%3A%2240132%22%2C%22title%22%3A%22%E7%94%B7%E5%AD%A9%E6%8B%BF%E5%A1%91%E6%96%99%E5%9C%88%E5%BD%93%E9%A3%9E%E9%95%96%E7%A0%B8%E4%B8%AD%E8%B7%AF%E4%BA%BA%E8%A2%AB%E6%8B%96%E6%8B%BD%22%7D&rank=&style_id=40132&topic_id=7617673858539356211",
          "hot": "560万",
          "platform": "toutiao"
        },
        {
          "rank": 22,
          "title": "14岁女孩被上铺舍友踩头致重伤",
          "url": "https://www.toutiao.com/trending/7617703490836889641/?category_name=topic_innerflow&event_type=hot_board&log_pb=%7B%22category_name%22%3A%22topic_innerflow%22%2C%22cluster_type%22%3A%228%22%2C%22enter_from%22%3A%22click_category%22%2C%22entrance_hotspot%22%3A%22outside%22%2C%22event_type%22%3A%22hot_board%22%2C%22hot_board_cluster_id%22%3A%227617703490836889641%22%2C%22hot_board_impr_id%22%3A%222026031616112915E2A6A4DD8510E97683%22%2C%22jump_page%22%3A%22hot_board_page%22%2C%22location%22%3A%22news_hot_card%22%2C%22page_location%22%3A%22hot_board_page%22%2C%22source%22%3A%22trending_tab%22%2C%22style_id%22%3A%2240132%22%2C%22title%22%3A%2214%E5%B2%81%E5%A5%B3%E5%AD%A9%E8%A2%AB%E4%B8%8A%E9%93%BA%E8%88%8D%E5%8F%8B%E8%B8%A9%E5%A4%B4%E8%87%B4%E9%87%8D%E4%BC%A4%22%7D&rank=&style_id=40132&topic_id=7617703490836889641",
          "hot": "507万",
          "platform": "toutiao"
        },
        {
          "rank": 23,
          "title": "315曝光漂白鸡爪 生产车间令人作呕",
          "url": "https://www.toutiao.com/trending/7617383931079491590/?category_name=topic_innerflow&event_type=hot_board&log_pb=%7B%22category_name%22%3A%22topic_innerflow%22%2C%22cluster_type%22%3A%221%22%2C%22enter_from%22%3A%22click_category%22%2C%22entrance_hotspot%22%3A%22outside%22%2C%22event_type%22%3A%22hot_board%22%2C%22hot_board_cluster_id%22%3A%227617383931079491590%22%2C%22hot_board_impr_id%22%3A%222026031616112915E2A6A4DD8510E97683%22%2C%22jump_page%22%3A%22hot_board_page%22%2C%22location%22%3A%22news_hot_card%22%2C%22page_location%22%3A%22hot_board_page%22%2C%22source%22%3A%22trending_tab%22%2C%22style_id%22%3A%2240132%22%2C%22title%22%3A%22315%E6%9B%9D%E5%85%89%E6%BC%82%E7%99%BD%E9%B8%A1%E7%88%AA+%E7%94%9F%E4%BA%A7%E8%BD%A6%E9%97%B4%E4%BB%A4%E4%BA%BA%E4%BD%9C%E5%91%95%22%7D&rank=&style_id=40132&topic_id=7617383931079491590",
          "hot": "459万",
          "platform": "toutiao"
        },
        {
          "rank": 24,
          "title": "日本小将松岛辉空成“王楚钦克星”",
          "url": "https://www.toutiao.com/trending/7617101324664946724/?category_name=topic_innerflow&event_type=hot_board&log_pb=%7B%22category_name%22%3A%22topic_innerflow%22%2C%22cluster_type%22%3A%223%22%2C%22enter_from%22%3A%22click_category%22%2C%22entrance_hotspot%22%3A%22outside%22%2C%22event_type%22%3A%22hot_board%22%2C%22hot_board_cluster_id%22%3A%227617101324664946724%22%2C%22hot_board_impr_id%22%3A%222026031616112915E2A6A4DD8510E97683%22%2C%22jump_page%22%3A%22hot_board_page%22%2C%22location%22%3A%22news_hot_card%22%2C%22page_location%22%3A%22hot_board_page%22%2C%22source%22%3A%22trending_tab%22%2C%22style_id%22%3A%2240132%22%2C%22title%22%3A%22%E6%97%A5%E6%9C%AC%E5%B0%8F%E5%B0%86%E6%9D%BE%E5%B2%9B%E8%BE%89%E7%A9%BA%E6%88%90%E2%80%9C%E7%8E%8B%E6%A5%9A%E9%92%A6%E5%85%8B%E6%98%9F%E2%80%9D%22%7D&rank=&style_id=40132&topic_id=7617101324664946724",
          "hot": "415万",
          "platform": "toutiao"
        },
        {
          "rank": 25,
          "title": "茅台是时候走下神坛了",
          "url": "https://www.toutiao.com/trending/7617680338344480306/?category_name=topic_innerflow&event_type=hot_board&log_pb=%7B%22category_name%22%3A%22topic_innerflow%22%2C%22cluster_type%22%3A%2213%22%2C%22enter_from%22%3A%22click_category%22%2C%22entrance_hotspot%22%3A%22outside%22%2C%22event_type%22%3A%22hot_board%22%2C%22hot_board_cluster_id%22%3A%227617680338344480306%22%2C%22hot_board_impr_id%22%3A%222026031616112915E2A6A4DD8510E97683%22%2C%22jump_page%22%3A%22hot_board_page%22%2C%22location%22%3A%22news_hot_card%22%2C%22page_location%22%3A%22hot_board_page%22%2C%22source%22%3A%22trending_tab%22%2C%22style_id%22%3A%2240132%22%2C%22title%22%3A%22%E8%8C%85%E5%8F%B0%E6%98%AF%E6%97%B6%E5%80%99%E8%B5%B0%E4%B8%8B%E7%A5%9E%E5%9D%9B%E4%BA%86%22%7D&rank=&style_id=40132&topic_id=7617680338344480306",
          "hot": "375万",
          "platform": "toutiao"
        },
        {
          "rank": 26,
          "title": "刘宇宁直播幽默回应未被黄子韬认出",
          "url": "https://www.toutiao.com/trending/7616698453997142058/?category_name=topic_innerflow&event_type=hot_board&log_pb=%7B%22category_name%22%3A%22topic_innerflow%22%2C%22cluster_type%22%3A%228%22%2C%22enter_from%22%3A%22click_category%22%2C%22entrance_hotspot%22%3A%22outside%22%2C%22event_type%22%3A%22hot_board%22%2C%22hot_board_cluster_id%22%3A%227616698453997142058%22%2C%22hot_board_impr_id%22%3A%222026031616112915E2A6A4DD8510E97683%22%2C%22jump_page%22%3A%22hot_board_page%22%2C%22location%22%3A%22news_hot_card%22%2C%22page_location%22%3A%22hot_board_page%22%2C%22source%22%3A%22trending_tab%22%2C%22style_id%22%3A%2240132%22%2C%22title%22%3A%22%E5%88%98%E5%AE%87%E5%AE%81%E7%9B%B4%E6%92%AD%E5%B9%BD%E9%BB%98%E5%9B%9E%E5%BA%94%E6%9C%AA%E8%A2%AB%E9%BB%84%E5%AD%90%E9%9F%AC%E8%AE%A4%E5%87%BA%22%7D&rank=&style_id=40132&topic_id=7616698453997142058",
          "hot": "340万",
          "platform": "toutiao"
        },
        {
          "rank": 27,
          "title": "95亿身家富豪入股西贝",
          "url": "https://www.toutiao.com/trending/7617211425760985142/?category_name=topic_innerflow&event_type=hot_board&log_pb=%7B%22category_name%22%3A%22topic_innerflow%22%2C%22cluster_type%22%3A%226%22%2C%22enter_from%22%3A%22click_category%22%2C%22entrance_hotspot%22%3A%22outside%22%2C%22event_type%22%3A%22hot_board%22%2C%22hot_board_cluster_id%22%3A%227617211425760985142%22%2C%22hot_board_impr_id%22%3A%222026031616112915E2A6A4DD8510E97683%22%2C%22jump_page%22%3A%22hot_board_page%22%2C%22location%22%3A%22news_hot_card%22%2C%22page_location%22%3A%22hot_board_page%22%2C%22source%22%3A%22trending_tab%22%2C%22style_id%22%3A%2240132%22%2C%22title%22%3A%2295%E4%BA%BF%E8%BA%AB%E5%AE%B6%E5%AF%8C%E8%B1%AA%E5%85%A5%E8%82%A1%E8%A5%BF%E8%B4%9D%22%7D&rank=&style_id=40132&topic_id=7617211425760985142",
          "hot": "307万",
          "platform": "toutiao"
        },
        {
          "rank": 28,
          "title": "315打假网红“万能神药”外泌体",
          "url": "https://www.toutiao.com/trending/7617477807379369498/?category_name=topic_innerflow&event_type=hot_board&log_pb=%7B%22category_name%22%3A%22topic_innerflow%22%2C%22cluster_type%22%3A%221%22%2C%22enter_from%22%3A%22click_category%22%2C%22entrance_hotspot%22%3A%22outside%22%2C%22event_type%22%3A%22hot_board%22%2C%22hot_board_cluster_id%22%3A%227617477807379369498%22%2C%22hot_board_impr_id%22%3A%222026031616112915E2A6A4DD8510E97683%22%2C%22jump_page%22%3A%22hot_board_page%22%2C%22location%22%3A%22news_hot_card%22%2C%22page_location%22%3A%22hot_board_page%22%2C%22source%22%3A%22trending_tab%22%2C%22style_id%22%3A%2240132%22%2C%22title%22%3A%22315%E6%89%93%E5%81%87%E7%BD%91%E7%BA%A2%E2%80%9C%E4%B8%87%E8%83%BD%E7%A5%9E%E8%8D%AF%E2%80%9D%E5%A4%96%E6%B3%8C%E4%BD%93%22%7D&rank=&style_id=40132&topic_id=7617477807379369498",
          "hot": "278万",
          "platform": "toutiao"
        },
        {
          "rank": 29,
          "title": "我国空间站中有座“老君的炼丹炉”",
          "url": "https://www.toutiao.com/trending/7617690212205858354/?category_name=topic_innerflow&event_type=hot_board&log_pb=%7B%22category_name%22%3A%22topic_innerflow%22%2C%22cluster_type%22%3A%2213%22%2C%22enter_from%22%3A%22click_category%22%2C%22entrance_hotspot%22%3A%22outside%22%2C%22event_type%22%3A%22hot_board%22%2C%22hot_board_cluster_id%22%3A%227617690212205858354%22%2C%22hot_board_impr_id%22%3A%222026031616112915E2A6A4DD8510E97683%22%2C%22jump_page%22%3A%22hot_board_page%22%2C%22location%22%3A%22news_hot_card%22%2C%22page_location%22%3A%22hot_board_page%22%2C%22source%22%3A%22trending_tab%22%2C%22style_id%22%3A%2240132%22%2C%22title%22%3A%22%E6%88%91%E5%9B%BD%E7%A9%BA%E9%97%B4%E7%AB%99%E4%B8%AD%E6%9C%89%E5%BA%A7%E2%80%9C%E8%80%81%E5%90%9B%E7%9A%84%E7%82%BC%E4%B8%B9%E7%82%89%E2%80%9D%22%7D&rank=&style_id=40132&topic_id=7617690212205858354",
          "hot": "251万",
          "platform": "toutiao"
        },
        {
          "rank": 30,
          "title": "西安环卫工被曝用长杆清除树上花朵",
          "url": "https://www.toutiao.com/trending/7617379619347742762/?category_name=topic_innerflow&event_type=hot_board&log_pb=%7B%22category_name%22%3A%22topic_innerflow%22%2C%22cluster_type%22%3A%226%22%2C%22enter_from%22%3A%22click_category%22%2C%22entrance_hotspot%22%3A%22outside%22%2C%22event_type%22%3A%22hot_board%22%2C%22hot_board_cluster_id%22%3A%227617379619347742762%22%2C%22hot_board_impr_id%22%3A%222026031616112915E2A6A4DD8510E97683%22%2C%22jump_page%22%3A%22hot_board_page%22%2C%22location%22%3A%22news_hot_card%22%2C%22page_location%22%3A%22hot_board_page%22%2C%22source%22%3A%22trending_tab%22%2C%22style_id%22%3A%2240132%22%2C%22title%22%3A%22%E8%A5%BF%E5%AE%89%E7%8E%AF%E5%8D%AB%E5%B7%A5%E8%A2%AB%E6%9B%9D%E7%94%A8%E9%95%BF%E6%9D%86%E6%B8%85%E9%99%A4%E6%A0%91%E4%B8%8A%E8%8A%B1%E6%9C%B5%22%7D&rank=&style_id=40132&topic_id=7617379619347742762",
          "hot": "227万",
          "platform": "toutiao"
        }
      ]
    }
  }
}